pypertrail/__init__.py
pypertrail/accounts.py
pypertrail/api.py
pypertrail/archives.py
pypertrail/cli.py
pypertrail/groups.py
pypertrail/saved_searches.py
pypertrail/search.py
pypertrail/systems.py
pypertrail/users.py
pypertrail/utils.py
pypertrail-1.0.0.dist-info/DESCRIPTION.rst
pypertrail-1.0.0.dist-info/METADATA
pypertrail-1.0.0.dist-info/RECORD
pypertrail-1.0.0.dist-info/WHEEL
pypertrail-1.0.0.dist-info/entry_points.txt
pypertrail-1.0.0.dist-info/metadata.json
pypertrail-1.0.0.dist-info/top_level.txt
tests/__init__.py
tests/test_pypertrail.py
