Metadata-Version: 2.0
Name: pypertrail
Version: 1.0.0
Summary: Python wrapper library and CLI for papertrail API.
Home-page: https://github.com/kwent/pypertrail
Author: Quentin Rousseau
Author-email: contact@quent.in
License: MIT license
Keywords: pypertrail
Platform: UNKNOWN
Classifier: Development Status :: 4 - Beta
Classifier: Intended Audience :: Developers
Classifier: License :: OSI Approved :: MIT License
Classifier: Natural Language :: English
Classifier: Programming Language :: Python :: 2.6
Classifier: Programming Language :: Python :: 2.7
Classifier: Programming Language :: Python :: 2
Classifier: Programming Language :: Python :: 3.3
Classifier: Programming Language :: Python :: 3.4
Classifier: Programming Language :: Python :: 3.5
Classifier: Programming Language :: Python :: 3
Classifier: Topic :: Internet :: WWW/HTTP
Classifier: Topic :: Software Development
Classifier: Topic :: System :: Logging
Classifier: Topic :: System :: Monitoring
Requires-Dist: Click (>=6.0)
Requires-Dist: PyYAML (>=3.12)
Requires-Dist: ansicolors (>=1.0.2)
Requires-Dist: requests (>=2.11.1)
